kerasplotlib/__init__.py
kerasplotlib/text.py
kerasplotlib/traininglog.py
kerasplotlib-1.0.dist-info/LICENSE
kerasplotlib-1.0.dist-info/METADATA
kerasplotlib-1.0.dist-info/WHEEL
kerasplotlib-1.0.dist-info/top_level.txt
kerasplotlib-1.0.dist-info/RECORD
